{
    "os": "Linux-5.4.0-146-generic-x86_64-with-glibc2.35",
    "python": "3.10.8",
    "heartbeatAt": "2023-09-14T11:31:23.921969",
    "startedAt": "2023-09-14T11:31:17.357970",
    "docker": null,
    "cuda": null,
    "args": [],
    "state": "running",
    "program": "/notebooks/rl2023/ex1/ex1.ipynb",
    "host": "jupyter-nguyenb5-rl2023",
    "username": "nguyenb5",
    "executable": "/opt/software/bin/python",
    "cpu_count": 8,
    "cpu_count_logical": 16,
    "cpu_freq": {
        "current": 2158.234125,
        "min": 1600.0,
        "max": 2666.0
    },
    "cpu_freq_per_core": [
        {
            "current": 2395.728,
            "min": 1600.0,
            "max": 2666.0
        },
        {
            "current": 2468.99,
            "min": 1600.0,
            "max": 2666.0
        },
        {
            "current": 2538.189,
            "min": 1600.0,
            "max": 2666.0
        },
        {
            "current": 1948.849,
            "min": 1600.0,
            "max": 2666.0
        },
        {
            "current": 1841.733,
            "min": 1600.0,
            "max": 2666.0
        },
        {
            "current": 2030.37,
            "min": 1600.0,
            "max": 2666.0
        },
        {
            "current": 2244.462,
            "min": 1600.0,
            "max": 2666.0
        },
        {
            "current": 1729.374,
            "min": 1600.0,
            "max": 2666.0
        },
        {
            "current": 2427.617,
            "min": 1600.0,
            "max": 2666.0
        },
        {
            "current": 1764.578,
            "min": 1600.0,
            "max": 2666.0
        },
        {
            "current": 2557.259,
            "min": 1600.0,
            "max": 2666.0
        },
        {
            "current": 2364.711,
            "min": 1600.0,
            "max": 2666.0
        },
        {
            "current": 1845.765,
            "min": 1600.0,
            "max": 2666.0
        },
        {
            "current": 2616.808,
            "min": 1600.0,
            "max": 2666.0
        },
        {
            "current": 1955.811,
            "min": 1600.0,
            "max": 2666.0
        },
        {
            "current": 1801.502,
            "min": 1600.0,
            "max": 2666.0
        }
    ],
    "disk": {
        "total": 134.24749755859375,
        "used": 97.0786247253418
    },
    "memory": {
        "total": 62.89131546020508
    }
}
